data_handler_ela/__init__.py
data_handler_ela/changers.py
data_handler_ela/checkers.py
data_handler_ela/util/__init__.py
data_handler_ela/util/evaluators.py
data_handler_ela/util/manipulators.py
data_handler_ela/util/recursors.py
data_handler_ela-0.1.7.dist-info/METADATA
data_handler_ela-0.1.7.dist-info/WHEEL
data_handler_ela-0.1.7.dist-info/RECORD
