Metadata-Version: 2.4
Name: data_handler_ela
Version: 0.1.7
Summary: all in one Complicated Data structure searching and altering tool
License: NONE
Author: Eliyas Wubie
Author-email: eliyas.wubie1@gmail.com
Requires-Python: >=3.10,<4.0
Classifier: License :: Other/Proprietary License
Classifier: Programming Language :: Python :: 3
Classifier: Programming Language :: Python :: 3.10
Classifier: Programming Language :: Python :: 3.11
Classifier: Programming Language :: Python :: 3.12
Classifier: Programming Language :: Python :: 3.13
Classifier: Programming Language :: Python :: 3.14
Requires-Dist: build (>=1.3.0,<2.0.0)
